{
  "species": "Feline",
  "breed": "Sphynx",
  "age": 1,
  "sex": "Male",
  "weight_kg": 3.5,
  "presenting_complaint": "Diarrhea and poor growth",
  "symptoms": [
    {"name": "Diarrhea", "onset": "3 weeks ago", "severity": "moderate", "progression": "chronic"},
    {"name": "Poor weight gain", "onset": "Since adoption", "severity": "mild", "progression": "chronic"}
  ],
  "history": {
    "chronic_diseases": [],
    "allergies": [],
    "previous_treatments": ["Deworming"],
    "vaccination_status": "Incomplete",
    "recent_travel": true,
    "contact_with_other_animals": true
  },
  "environment": {
    "living": "Indoor",
    "diet": "Kitten food",
    "exposures": ["Other cats"]
  },
  "owner_concerns": "Kitten is active but not growing as expected."
}